setup.cfg
setup.py
alooma_hvac.egg-info/PKG-INFO
alooma_hvac.egg-info/SOURCES.txt
alooma_hvac.egg-info/dependency_links.txt
alooma_hvac.egg-info/requires.txt
alooma_hvac.egg-info/top_level.txt
hvac/__init__.py
hvac/exceptions.py
hvac/tests/__init__.py
hvac/tests/test_integration.py
hvac/tests/util.py
hvac/v1/__init__.py