Metadata-Version: 1.1
Name: alooma-hvac
Version: 0.2.18
Summary: HashiCorp Vault API client
Home-page: https://github.com/Aloomaio/alooma-hvac
Author: Ram Amar
Author-email: rami@alooma.com
License: UNKNOWN
Keywords: hashicorp,vault
Platform: UNKNOWN
Classifier: License :: OSI Approved :: Apache Software License
